{".class":"MypyFile","_fullname":"dsp.modules.sbert","future_import_flags":[],"is_partial_stub_package":false,"is_stub":false,"names":{".class":"SymbolTable","SentenceTransformersCrossEncoder":{".class":"SymbolTableNode","kind":"Gdef","node":{".class":"TypeInfo","_promote":[],"abstract_attributes":[],"alt_promote":null,"bases":["builtins.object"],"dataclass_transform_spec":null,"declared_metaclass":null,"defn":{".class":"ClassDef","fullname":"dsp.modules.sbert.SentenceTransformersCrossEncoder","name":"SentenceTransformersCrossEncoder","type_vars":[]},"deletable_attributes":[],"flags":[],"fullname":"dsp.modules.sbert.SentenceTransformersCrossEncoder","has_param_spec_type":false,"metaclass_type":null,"metadata":{},"module_name":"dsp.modules.sbert","mro":["dsp.modules.sbert.SentenceTransformersCrossEncoder","builtins.object"],"names":{".class":"SymbolTable","__call__":{".class":"SymbolTableNode","kind":"Mdef","node":{".class":"FuncDef","abstract_status":0,"arg_kinds":[0,0,0],"arg_names":["self","query","passage"],"dataclass_transform_spec":null,"flags":[],"fullname":"dsp.modules.sbert.SentenceTransformersCrossEncoder.__call__","name":"__call__","type":{".class":"CallableType","arg_kinds":[0,0,0],"arg_names":["self","query","passage"],"arg_types":["dsp.modules.sbert.SentenceTransformersCrossEncoder","builtins.str",{".class":"Instance","args":["builtins.str"],"type_ref":"builtins.list"}],"bound_args":[],"def_extras":{"first_arg":"self"},"fallback":"builtins.function","from_concatenate":false,"implicit":false,"imprecise_arg_kinds":false,"is_ellipsis_args":false,"name":"__call__ of SentenceTransformersCrossEncoder","ret_type":{".class":"Instance","args":["builtins.float"],"type_ref":"builtins.list"},"type_guard":null,"unpack_kwargs":false,"variables":[]}}},"__init__":{".class":"SymbolTableNode","kind":"Mdef","node":{".class":"FuncDef","abstract_status":0,"arg_kinds":[0,1],"arg_names":["self","model_name_or_path"],"dataclass_transform_spec":null,"flags":[],"fullname":"dsp.modules.sbert.SentenceTransformersCrossEncoder.__init__","name":"__init__","type":{".class":"CallableType","arg_kinds":[0,1],"arg_names":["self","model_name_or_path"],"arg_types":["dsp.modules.sbert.SentenceTransformersCrossEncoder","builtins.str"],"bound_args":[],"def_extras":{"first_arg":"self"},"fallback":"builtins.function","from_concatenate":false,"implicit":false,"imprecise_arg_kinds":false,"is_ellipsis_args":false,"name":"__init__ of SentenceTransformersCrossEncoder","ret_type":{".class":"NoneType"},"type_guard":null,"unpack_kwargs":false,"variables":[]}}},"model":{".class":"SymbolTableNode","implicit":true,"kind":"Mdef","node":{".class":"Var","flags":["is_inferred"],"fullname":"dsp.modules.sbert.SentenceTransformersCrossEncoder.model","name":"model","type":{".class":"AnyType","missing_import_name":"dsp.modules.sbert.SentenceTransformersCrossEncoder.CrossEncoder","source_any":{".class":"AnyType","missing_import_name":"dsp.modules.sbert.SentenceTransformersCrossEncoder.CrossEncoder","source_any":null,"type_of_any":3},"type_of_any":7}}}},"self_type":{".class":"TypeVarType","default":{".class":"AnyType","missing_import_name":null,"source_any":null,"type_of_any":4},"fullname":"dsp.modules.sbert.SentenceTransformersCrossEncoder.Self","id":0,"name":"Self","namespace":"","upper_bound":"dsp.modules.sbert.SentenceTransformersCrossEncoder","values":[],"variance":0},"slots":null,"tuple_type":null,"type_vars":[],"typeddict_type":null}},"__annotations__":{".class":"SymbolTableNode","kind":"Gdef","node":{".class":"Var","flags":["is_ready"],"fullname":"dsp.modules.sbert.__annotations__","name":"__annotations__","type":{".class":"Instance","args":["builtins.str",{".class":"AnyType","missing_import_name":null,"source_any":null,"type_of_any":6}],"type_ref":"builtins.dict"}}},"__doc__":{".class":"SymbolTableNode","kind":"Gdef","node":{".class":"Var","flags":["is_ready"],"fullname":"dsp.modules.sbert.__doc__","name":"__doc__","type":"builtins.str"}},"__file__":{".class":"SymbolTableNode","kind":"Gdef","node":{".class":"Var","flags":["is_ready"],"fullname":"dsp.modules.sbert.__file__","name":"__file__","type":"builtins.str"}},"__name__":{".class":"SymbolTableNode","kind":"Gdef","node":{".class":"Var","flags":["is_ready"],"fullname":"dsp.modules.sbert.__name__","name":"__name__","type":"builtins.str"}},"__package__":{".class":"SymbolTableNode","kind":"Gdef","node":{".class":"Var","flags":["is_ready"],"fullname":"dsp.modules.sbert.__package__","name":"__package__","type":"builtins.str"}}},"path":"/home/anchit/dspy/dsp/modules/sbert.py"}